Metadata-Version: 1.1
Name: auepa
Version: 0.1
Summary: Another Unofficial EmojiPedia API.
Home-page: https://github.com/kubinka0505/auepa
Author: kubinka0505
Author-email: UNKNOWN
License: GPL V3
Keywords: auepa image emojipedia api api-wrapper
Platform: UNKNOWN
Classifier: Development Status :: 4 - Beta
Classifier: Environment :: Console
Classifier: Intended Audience :: End Users/Desktop
Classifier: License :: OSI Approved :: GNU General Public License v3 (GPLv3)
Classifier: Natural Language :: English
Classifier: Programming Language :: Python :: 3 :: Only
Classifier: Topic :: Utilities
